{
  "verdict": "needs-work",
  "summary": "Two blocking issues: a non-word entry (6A) and an answer echoed in its own clue (7A). Plus minor style nits.",
  "findings": [
    {
      "location": "6A",
      "severity": "high",
      "category": "fill",
      "issue": "OOXTE is not a word, name, or phrase.",
      "suggestion": "Replace this entry — requires a grid change, not a re-clue."
    },
    {
      "location": "7A",
      "severity": "high",
      "category": "duplicate",
      "issue": "The clue 'Rat, for one' contains the answer word RAT.",
      "suggestion": "Reclue without the word 'rat' (e.g. a synonym/wordplay angle)."
    },
    {
      "location": "1A",
      "severity": "low",
      "category": "style",
      "issue": "Fine clue, but a livelier Saturday angle is available.",
      "suggestion": "Consider a wittier misdirection."
    }
  ]
}
